prestoweb/__init__.py
prestoweb/manage.py
prestoweb/prestoweb-runserver
prestoweb/app/__init__.py
prestoweb/app/admin.py
prestoweb/app/apps.py
prestoweb/app/models.py
prestoweb/app/tests.py
prestoweb/app/views.py
prestoweb/app/migrations/__init__.py
prestoweb/prestoweb/__init__.py
prestoweb/prestoweb/settings.py
prestoweb/prestoweb/urls.py
prestoweb/prestoweb/wsgi.py
prestoweb-0.19.0.data/scripts/prestoweb-runserver
prestoweb-0.19.0.dist-info/LICENSE
prestoweb-0.19.0.dist-info/METADATA
prestoweb-0.19.0.dist-info/WHEEL
prestoweb-0.19.0.dist-info/entry_points.txt
prestoweb-0.19.0.dist-info/top_level.txt
prestoweb-0.19.0.dist-info/RECORD
