Metadata-Version: 2.1
Name: prestoweb
Version: 0.19.0
Summary: Prediction for Surgical Treatment and Oncology (PRESTO)
Home-page: https://github.com/rbrecheisen/prestoweb
Author: Ralph Brecheisen
Author-email: r.brecheisen@maastrichtuniversity.nl
License: MIT license
Keywords: prestoweb
Platform: UNKNOWN
Classifier: Development Status :: 2 - Pre-Alpha
Classifier: Intended Audience :: Developers
Classifier: License :: OSI Approved :: MIT License
Classifier: Natural Language :: English
Classifier: Programming Language :: Python :: 3
Classifier: Programming Language :: Python :: 3.5
Classifier: Programming Language :: Python :: 3.6
Classifier: Programming Language :: Python :: 3.7
Classifier: Programming Language :: Python :: 3.8
Requires-Python: >=3.5
Requires-Dist: django
Requires-Dist: djangorestframework
Requires-Dist: django-session-security
Requires-Dist: uwsgi
